Bruhapi/__init__.py
Bruhapi/bruh.py
Bruhapi/things.py
Bruhapi-0.0.2.dist-info/LICENSE
Bruhapi-0.0.2.dist-info/METADATA
Bruhapi-0.0.2.dist-info/WHEEL
Bruhapi-0.0.2.dist-info/top_level.txt
Bruhapi-0.0.2.dist-info/RECORD
