Metadata-Version: 2.1
Name: Bruhapi
Version: 0.0.2
Summary: UNKNOWN
Home-page: https://github.com/sldless/Bruhapi
Author: sldless
License: MIT
Platform: UNKNOWN
Classifier: Programming Language :: Python :: 3
Classifier: License :: OSI Approved :: MIT License
Classifier: Operating System :: OS Independent
Requires-Python: >=3.6
Requires-Dist: aiohttp
